{
	"info": {
		"_postman_id": "f1c4f65e-c993-43bc-ab26-4f7b08d99df3",
		"name": "bookFrunish",
		"schema": "https://schema.getpostman.com/json/collection/v2.1.0/collection.json"
	},
	"item": [
		{
			"name": "book",
			"item": [
				{
					"name": "Create Book",
					"request": {
						"method": "POST",
						"header": [
							{
								"key": "Content-Type",
								"name": "Content-Type",
								"value": "application/json",
								"type": "text"
							}
						],
						"body": {
							"mode": "raw",
							"raw": "{\n\t\"category\" : \"hhh\",\n\t\"bookName\" : \"hhh 1\",\n\t\"bookType\" : \"notes\",\n\t\"isAvailable\" : \"true\",\n\t\"tag\" : [\"sss\", \"suraj\"]\n}"
						},
						"url": {
							"raw": "http://localhost:8000/api/v1/book/",
							"protocol": "http",
							"host": [
								"localhost"
							],
							"port": "8000",
							"path": [
								"api",
								"v1",
								"book",
								""
							]
						}
					},
					"response": []
				},
				{
					"name": "getAllBook",
					"request": {
						"method": "GET",
						"header": [],
						"url": {
							"raw": "http://localhost:8000/api/v1/book/",
							"protocol": "http",
							"host": [
								"localhost"
							],
							"port": "8000",
							"path": [
								"api",
								"v1",
								"book",
								""
							]
						}
					},
					"response": []
				},
				{
					"name": "getBookById",
					"request": {
						"method": "GET",
						"header": [],
						"url": {
							"raw": "http://localhost:8000/api/v1/book/5e4766e6477a322b3c147a3a",
							"protocol": "http",
							"host": [
								"localhost"
							],
							"port": "8000",
							"path": [
								"api",
								"v1",
								"book",
								"5e4766e6477a322b3c147a3a"
							]
						}
					},
					"response": []
				},
				{
					"name": "updateBook",
					"request": {
						"method": "PATCH",
						"header": [
							{
								"key": "Content-Type",
								"name": "Content-Type",
								"value": "application/json",
								"type": "text"
							}
						],
						"body": {
							"mode": "raw",
							"raw": "{\n\t\"category\" : \"Test Update\",\n\t\"bookName\" : \"Test Update\",\n\t\"bookType\" : \"notes\",\n\t\"isAvailable\" : \"true\"\n}"
						},
						"url": {
							"raw": "http://localhost:8000/api/v1/book/5e4766e6477a322b3c147a3a",
							"protocol": "http",
							"host": [
								"localhost"
							],
							"port": "8000",
							"path": [
								"api",
								"v1",
								"book",
								"5e4766e6477a322b3c147a3a"
							]
						}
					},
					"response": []
				},
				{
					"name": "deleteBook",
					"request": {
						"method": "DELETE",
						"header": [],
						"url": {
							"raw": "http://localhost:8000/api/v1/book/5e4766e6477a322b3c147a3a",
							"protocol": "http",
							"host": [
								"localhost"
							],
							"port": "8000",
							"path": [
								"api",
								"v1",
								"book",
								"5e4766e6477a322b3c147a3a"
							]
						}
					},
					"response": []
				}
			]
		},
		{
			"name": "user",
			"item": [
				{
					"name": "createUser",
					"request": {
						"method": "POST",
						"header": [
							{
								"key": "Content-Type",
								"name": "Content-Type",
								"value": "application/json",
								"type": "text"
							}
						],
						"body": {
							"mode": "raw",
							"raw": "{\n\t\"name\": \"hero2\",\n\t\"email\": \"her22o123@gmail.com\",\n\t\"password\" : \"12345678922\",\n\t\"branch\" : \"CSE\",\n\t\"semester\": 5,\n\t\"enrollmentNo\" : 1803051032100\n}"
						},
						"url": {
							"raw": "http://localhost:8000/api/v1/user/",
							"protocol": "http",
							"host": [
								"localhost"
							],
							"port": "8000",
							"path": [
								"api",
								"v1",
								"user",
								""
							]
						}
					},
					"response": []
				},
				{
					"name": "getAllUser",
					"request": {
						"method": "GET",
						"header": [],
						"url": {
							"raw": "http://localhost:8000/api/v1/user/",
							"protocol": "http",
							"host": [
								"localhost"
							],
							"port": "8000",
							"path": [
								"api",
								"v1",
								"user",
								""
							]
						}
					},
					"response": []
				},
				{
					"name": "updateUser",
					"request": {
						"method": "PATCH",
						"header": [
							{
								"key": "Content-Type",
								"name": "Content-Type",
								"value": "application/json",
								"type": "text"
							}
						],
						"body": {
							"mode": "raw",
							"raw": "{\n\t\"name\": \"he11\",\n\t\"email\": \"her2223@gmail.com\",\n\t\"password\" : \"1235678922\",\n\t\"branch\" : \"CSE\",\n\t\"semester\": 5,\n\t\"enrollmentNo\" : 1803051032100\n}"
						},
						"url": {
							"raw": "http://localhost:8000/api/v1/user/5e476beb1b4feb30b72eb13d",
							"protocol": "http",
							"host": [
								"localhost"
							],
							"port": "8000",
							"path": [
								"api",
								"v1",
								"user",
								"5e476beb1b4feb30b72eb13d"
							]
						}
					},
					"response": []
				},
				{
					"name": "getUserById",
					"request": {
						"method": "GET",
						"header": [],
						"url": {
							"raw": "http://localhost:8000/api/v1/user/5e476beb1b4feb30b72eb13d",
							"protocol": "http",
							"host": [
								"localhost"
							],
							"port": "8000",
							"path": [
								"api",
								"v1",
								"user",
								"5e476beb1b4feb30b72eb13d"
							]
						}
					},
					"response": []
				},
				{
					"name": "deleteUser",
					"request": {
						"method": "DELETE",
						"header": [],
						"url": {
							"raw": "http://localhost:8000/api/v1/user/5e476beb1b4feb30b72eb13d",
							"protocol": "http",
							"host": [
								"localhost"
							],
							"port": "8000",
							"path": [
								"api",
								"v1",
								"user",
								"5e476beb1b4feb30b72eb13d"
							]
						}
					},
					"response": []
				}
			]
		},
		{
			"name": "borrow",
			"item": [
				{
					"name": "createRecord",
					"request": {
						"method": "POST",
						"header": [
							{
								"key": "Content-Type",
								"name": "Content-Type",
								"type": "text",
								"value": "application/json"
							}
						],
						"body": {
							"mode": "raw",
							"raw": "{\n\t\"bookID\" : \"5e476b96854bc130f55eed28\",\n\t\"userID\" : \"5e476d93d6595025ef66b7f1\"\n}"
						},
						"url": {
							"raw": "http://localhost:8000/api/v1/borrow/",
							"protocol": "http",
							"host": [
								"localhost"
							],
							"port": "8000",
							"path": [
								"api",
								"v1",
								"borrow",
								""
							]
						}
					},
					"response": []
				},
				{
					"name": "getAllRecord",
					"request": {
						"method": "GET",
						"header": [],
						"url": {
							"raw": "http://localhost:8000/api/v1/borrow/",
							"protocol": "http",
							"host": [
								"localhost"
							],
							"port": "8000",
							"path": [
								"api",
								"v1",
								"borrow",
								""
							]
						}
					},
					"response": []
				},
				{
					"name": "getRecordByUserID",
					"request": {
						"method": "GET",
						"header": [],
						"url": {
							"raw": "http://localhost:8000/api/v1/borrow/5e476d93d6595025ef66b7f1",
							"protocol": "http",
							"host": [
								"localhost"
							],
							"port": "8000",
							"path": [
								"api",
								"v1",
								"borrow",
								"5e476d93d6595025ef66b7f1"
							]
						}
					},
					"response": []
				},
				{
					"name": "deleteRecord",
					"request": {
						"method": "DELETE",
						"header": [],
						"url": {
							"raw": "http://localhost:8000/api/v1/borrow/5e478e2ac1ba2a11a6c4ceaf",
							"protocol": "http",
							"host": [
								"localhost"
							],
							"port": "8000",
							"path": [
								"api",
								"v1",
								"borrow",
								"5e478e2ac1ba2a11a6c4ceaf"
							]
						}
					},
					"response": []
				}
			]
		}
	]
}